wavedl/__init__.py
wavedl/hpo.py
wavedl/launcher.py
wavedl/test.py
wavedl/train.py
wavedl/models/__init__.py
wavedl/models/_pretrained_utils.py
wavedl/models/_template.py
wavedl/models/base.py
wavedl/models/caformer.py
wavedl/models/cnn.py
wavedl/models/convnext.py
wavedl/models/convnext_v2.py
wavedl/models/densenet.py
wavedl/models/efficientnet.py
wavedl/models/efficientnetv2.py
wavedl/models/efficientvit.py
wavedl/models/fastvit.py
wavedl/models/mamba.py
wavedl/models/maxvit.py
wavedl/models/mobilenetv3.py
wavedl/models/registry.py
wavedl/models/regnet.py
wavedl/models/resnet.py
wavedl/models/resnet3d.py
wavedl/models/swin.py
wavedl/models/tcn.py
wavedl/models/unet.py
wavedl/models/unireplknet.py
wavedl/models/vit.py
wavedl/utils/__init__.py
wavedl/utils/config.py
wavedl/utils/constraints.py
wavedl/utils/cross_validation.py
wavedl/utils/data.py
wavedl/utils/distributed.py
wavedl/utils/losses.py
wavedl/utils/metrics.py
wavedl/utils/optimizers.py
wavedl/utils/schedulers.py
wavedl-1.6.2.dist-info/LICENSE
wavedl-1.6.2.dist-info/METADATA
wavedl-1.6.2.dist-info/WHEEL
wavedl-1.6.2.dist-info/entry_points.txt
wavedl-1.6.2.dist-info/top_level.txt
wavedl-1.6.2.dist-info/RECORD
