Metadata-Version: 2.2
Name: wavedl
Version: 1.6.2
Summary: A Scalable Deep Learning Framework for Wave-Based Inverse Problems
Author: Ductho Le
License: MIT
Project-URL: Homepage, https://github.com/ductho-le/WaveDL
Project-URL: Repository, https://github.com/ductho-le/WaveDL
Project-URL: Documentation, https://github.com/ductho-le/WaveDL#readme
Project-URL: Issues, https://github.com/ductho-le/WaveDL/issues
Keywords: deep-learning,inverse-problems,wave-propagation,ultrasonic,guided-waves,non-destructive-testing,machine-learning,pytorch,regression
Classifier: Development Status :: 4 - Beta
Classifier: Intended Audience :: Science/Research
Classifier: License :: OSI Approved :: MIT License
Classifier: Programming Language :: Python :: 3
Classifier: Programming Language :: Python :: 3.11
Classifier: Programming Language :: Python :: 3.12
Classifier: Programming Language :: Python :: 3.13
Classifier: Topic :: Scientific/Engineering :: Artificial Intelligence
Classifier: Topic :: Scientific/Engineering :: Physics
Requires-Python: >=3.11
License-File: LICENSE
Requires-Dist: torch>=2.0.0
Requires-Dist: torchvision>=0.15.0
Requires-Dist: timm>=0.9.0
Requires-Dist: accelerate>=0.20.0
Requires-Dist: numpy>=1.24.0
Requires-Dist: scipy>=1.10.0
Requires-Dist: scikit-learn>=1.2.0
Requires-Dist: pandas>=2.0.0
Requires-Dist: matplotlib>=3.7.0
Requires-Dist: tqdm>=4.65.0
Requires-Dist: pyyaml>=6.0.0
Requires-Dist: h5py>=3.8.0
Requires-Dist: safetensors>=0.3.0
Requires-Dist: wandb>=0.15.0
Requires-Dist: optuna>=3.0.0
Requires-Dist: onnx>=1.14.0
Requires-Dist: onnxruntime>=1.15.0
Requires-Dist: onnxscript>=0.1.0
Requires-Dist: triton>=2.0.0; sys_platform == "linux"
Provides-Extra: dev
Requires-Dist: pytest>=7.0.0; extra == "dev"
Requires-Dist: pytest-xdist>=3.5.0; extra == "dev"
Requires-Dist: ruff>=0.8.0; extra == "dev"
Requires-Dist: pre-commit>=3.5.0; extra == "dev"
